{
  "loseInventory": false,
  "restrictMenuAccess": true,
  "creativePlayerDropHeads": false,
  "leaveReviveStructureBase": true,
  "soul_sand_blocks": [
    2631,
    2630,
    2634,
    2641,
    2637,
    2635,
    2642,
    257,
    2633,
    2632,
    258,
    2636,
    2638,
    2640,
    2639
  ],
  "flower_blocks": [
    159,
    378
  ],
  "ore_blocks": [
    1111,
    164,
    840,
    347,
    163,
    181
  ],
  "fence_blocks": [
    8747,
    8668,
    817,
    575,
    8843,
    1092,
    9121,
    816,
    1070,
    8649,
    577,
    8962,
    578,
    579,
    580,
    8604,
    582,
    326,
    8786,
    1048,
    8963,
    8824,
    8988,
    8623,
    576,
    8805,
    254,
    8725,
    8767,
    8706,
    1026,
    581,
    8687
  ],
  "stair_blocks": [
    458,
    9056,
    972,
    745,
    471,
    461,
    176,
    8745,
    736,
    9030,
    9129,
    9153,
    457,
    9154,
    739,
    8986,
    9068,
    470,
    9152,
    9141,
    9074,
    9151,
    9128,
    930,
    948,
    732,
    8685,
    322,
    823,
    8647,
    538,
    348,
    9084,
    946,
    738,
    741,
    8527,
    737,
    9052,
    9039,
    8548,
    742,
    740,
    9077,
    8515,
    1046,
    327,
    1068,
    822,
    472,
    8784,
    733,
    984,
    8704,
    932,
    8621,
    8666,
    9130,
    9088,
    1024,
    947,
    931,
    9127,
    422,
    8602,
    735,
    8519,
    321,
    858,
    460,
    8803,
    9071,
    744,
    8504,
    945,
    9043,
    9163,
    349,
    596,
    8531,
    9120,
    9080,
    459,
    9142,
    9065,
    976,
    198,
    980,
    861,
    9061,
    734,
    9165,
    9166,
    320,
    341,
    8822,
    1090,
    9048,
    462,
    8841,
    743,
    929,
    8968,
    9035,
    8765,
    8723,
    350,
    850,
    9139,
    9140,
    8508,
    9164
  ]
}